zmq_ses_communications/__init__.py
zmq_ses_communications/client/Device.py
zmq_ses_communications/client/__init__.py
zmq_ses_communications/client/async_pub.py
zmq_ses_communications/client/async_sub.py
zmq_ses_communications/client/msgs/__init__.py
zmq_ses_communications/client/msgs/command_pb2.py
zmq_ses_communications/client/msgs/heartbeat_pb2.py
zmq_ses_communications/client/pub_sub_node.py
zmq_ses_communications/client/reply.py
zmq_ses_communications/client/req_res_node.py
zmq_ses_communications/client/request.py
zmq_ses_communications/server/__init__.py
zmq_ses_communications/server/broker.py
zmq_ses_communications/server/pub_sub_router.py
zmq_ses_communications/server/req_res_router.py
zmq_ses_communications/tests/async_clinet_server.py
zmq_ses_communications/tests/broker_test.py
zmq_ses_communications/tests/client_test.py
zmq_ses_communications/tests/client_test_2.py
zmq_ses_communications/tests/client_test_3.py
zmq_ses_communications/tests/client_test_req_res.py
zmq_ses_communications/tests/ses_helpers.py
zmq_ses_communications/tests/ses_node.py
zmq_ses_communications/tests/ses_publisher.py
zmq_ses_communications/tests/ses_subscriber.py
zmq_ses_communications/tests/test_proto.py
zmq_ses_communications/tests/trace_mem.py
zmq_ses_communications-0.1.2.dist-info/LICENSE
zmq_ses_communications-0.1.2.dist-info/WHEEL
zmq_ses_communications-0.1.2.dist-info/METADATA
zmq_ses_communications-0.1.2.dist-info/RECORD
